placards/__init__.py
placards/__main__.py
placards/__version__.py
placards/config.py
placards/errors.py
placards/platform.py
placards/html/index.html
placards-0.0.18.data/data/index.html
placards-0.0.18.data/scripts/placards
placards-0.0.18.dist-info/METADATA
placards-0.0.18.dist-info/WHEEL
placards-0.0.18.dist-info/top_level.txt
placards-0.0.18.dist-info/RECORD
