Metadata-Version: 2.4
Name: placards
Version: 0.0.18
Summary: A placards digital signage client for Linux in Python
Author: Ben Timby
Author-email: btimby@gmail.com
Classifier: Development Status :: 5 - Production/Stable
Classifier: Intended Audience :: Developers
Classifier: License :: OSI Approved :: MIT License
Classifier: Programming Language :: Python :: 3
Classifier: Programming Language :: Python :: 3.6
Requires-Dist: pyppeteer
Requires-Dist: aiohttp
Dynamic: author
Dynamic: author-email
Dynamic: classifier
Dynamic: description
Dynamic: requires-dist
Dynamic: summary
